telepot/__init__.py
telepot/api.py
telepot/delegate.py
telepot/exception.py
telepot/filtering.py
telepot/hack.py
telepot/helper.py
telepot/loop.py
telepot/namedtuple.py
telepot/routing.py
telepot/test_settings.py
telepot/text.py
telepot/utils.py
telepot/aio/__init__.py
telepot/aio/api.py
telepot/aio/delegate.py
telepot/aio/hack.py
telepot/aio/helper.py
telepot/aio/loop.py
telepot/aio/routing.py
telepota-1.0.dist-info/LICENSE.md
telepota-1.0.dist-info/METADATA
telepota-1.0.dist-info/WHEEL
telepota-1.0.dist-info/top_level.txt
telepota-1.0.dist-info/RECORD
