Metadata-Version: 2.1
Name: telepota
Version: 1.0
Summary: Python framework for Telegram Bot API
Home-page: https://github.com/codingsett/telepota
Author: Joseph Kuria
Author-email: josephkiurire@outlook.com
License: MIT
Keywords: telegram bot api python wrapper telepota framework
Platform: UNKNOWN
Classifier: Development Status :: 5 - Production/Stable
Classifier: Intended Audience :: Developers
Classifier: Topic :: Software Development :: Libraries :: Python Modules
Classifier: Topic :: Communications :: Chat
Classifier: License :: OSI Approved :: MIT License
Classifier: Programming Language :: Python :: 3
Classifier: Programming Language :: Python :: 3.2
Classifier: Programming Language :: Python :: 3.3
Classifier: Programming Language :: Python :: 3.4
Classifier: Programming Language :: Python :: 3.5
Classifier: Programming Language :: Python :: 3.6
Requires-Dist: urllib3 (>=1.25.1)
Requires-Dist: pycryptodomex (>=3.9.8)
Requires-Dist: aiohttp (>=3.0.0)
